odoo/addons/web_copy_confirm/README.rst
odoo/addons/web_copy_confirm/__init__.py
odoo/addons/web_copy_confirm/__manifest__.py
odoo/addons/web_copy_confirm/i18n/de.po
odoo/addons/web_copy_confirm/i18n/fr.po
odoo/addons/web_copy_confirm/i18n/it.po
odoo/addons/web_copy_confirm/i18n/web_copy_confirm.pot
odoo/addons/web_copy_confirm/readme/CONTRIBUTORS.md
odoo/addons/web_copy_confirm/readme/DESCRIPTION.md
odoo/addons/web_copy_confirm/readme/HISTORY.md
odoo/addons/web_copy_confirm/static/description/icon.png
odoo/addons/web_copy_confirm/static/description/index.html
odoo/addons/web_copy_confirm/static/src/js/web_copy_confirm.esm.js
odoo/addons/web_copy_confirm/static/tests/confirm.test.js
odoo_addon_web_copy_confirm-18.0.1.0.0.2.dist-info/METADATA
odoo_addon_web_copy_confirm-18.0.1.0.0.2.dist-info/WHEEL
odoo_addon_web_copy_confirm-18.0.1.0.0.2.dist-info/top_level.txt
odoo_addon_web_copy_confirm-18.0.1.0.0.2.dist-info/RECORD
